alibabacloud_ehpc20240730/__init__.py
alibabacloud_ehpc20240730/client.py
alibabacloud_ehpc20240730/models/__init__.py
alibabacloud_ehpc20240730/models/_addon_node_template.py
alibabacloud_ehpc20240730/models/_attach_nodes_request.py
alibabacloud_ehpc20240730/models/_attach_nodes_response.py
alibabacloud_ehpc20240730/models/_attach_nodes_response_body.py
alibabacloud_ehpc20240730/models/_attach_nodes_shrink_request.py
alibabacloud_ehpc20240730/models/_attach_shared_storages_request.py
alibabacloud_ehpc20240730/models/_attach_shared_storages_response.py
alibabacloud_ehpc20240730/models/_attach_shared_storages_response_body.py
alibabacloud_ehpc20240730/models/_attach_shared_storages_shrink_request.py
alibabacloud_ehpc20240730/models/_create_cluster_request.py
alibabacloud_ehpc20240730/models/_create_cluster_response.py
alibabacloud_ehpc20240730/models/_create_cluster_response_body.py
alibabacloud_ehpc20240730/models/_create_cluster_shrink_request.py
alibabacloud_ehpc20240730/models/_create_job_request.py
alibabacloud_ehpc20240730/models/_create_job_response.py
alibabacloud_ehpc20240730/models/_create_job_response_body.py
alibabacloud_ehpc20240730/models/_create_job_shrink_request.py
alibabacloud_ehpc20240730/models/_create_nodes_request.py
alibabacloud_ehpc20240730/models/_create_nodes_response.py
alibabacloud_ehpc20240730/models/_create_nodes_response_body.py
alibabacloud_ehpc20240730/models/_create_nodes_shrink_request.py
alibabacloud_ehpc20240730/models/_create_queue_request.py
alibabacloud_ehpc20240730/models/_create_queue_response.py
alibabacloud_ehpc20240730/models/_create_queue_response_body.py
alibabacloud_ehpc20240730/models/_create_queue_shrink_request.py
alibabacloud_ehpc20240730/models/_create_reserved_node_pool_request.py
alibabacloud_ehpc20240730/models/_create_reserved_node_pool_response.py
alibabacloud_ehpc20240730/models/_create_reserved_node_pool_response_body.py
alibabacloud_ehpc20240730/models/_create_users_request.py
alibabacloud_ehpc20240730-2.3.0.dist-info/LICENSE
alibabacloud_ehpc20240730-2.3.0.dist-info/METADATA
alibabacloud_ehpc20240730-2.3.0.dist-info/WHEEL
alibabacloud_ehpc20240730-2.3.0.dist-info/top_level.txt
alibabacloud_ehpc20240730-2.3.0.dist-info/RECORD
